<?xml version="1.0" encoding="UTF-8"?>
<!DOCTYPE pkgmetadata SYSTEM "http://www.gentoo.org/dtd/metadata.dtd">
<pkgmetadata>
  <longdescription>
    SquidClamAV is a <pkg>net-proxy/squid</pkg> redirector which allows easy antivirus file
    scanning.  It can use either a local or a remote ClamAV daemon. As
    of version 6.0, it is now an ICAP module for
    <pkg>net-proxy/c-icap</pkg>.
  </longdescription>
  <upstream>
    <remote-id type="sourceforge">squidclamav</remote-id>
  </upstream>
</pkgmetadata>
