<?xml version="1.0" encoding="UTF-8"?>
<!DOCTYPE pkgmetadata SYSTEM "https://www.gentoo.org/dtd/metadata.dtd">
<pkgmetadata>
	<maintainer type="person">
		<email>grozin@gentoo.org</email>
		<name>Andrey Grozin</name>
	</maintainer>
	<maintainer type="person" proxied="yes">
		<email>joaompssantos@gmail.com</email>
		<name>Joao Santos</name>
	</maintainer>
	<maintainer type="project" proxied="proxy">
		<email>proxy-maint@gentoo.org</email>
		<name>Proxy Maintainers</name>
	</maintainer>
</pkgmetadata>
