<?xml version="1.0" encoding="UTF-8"?>
<!DOCTYPE pkgmetadata SYSTEM "http://www.gentoo.org/dtd/metadata.dtd">
<pkgmetadata>
	<maintainer type="person">
		<email>jss2k2@chello.no</email>
		<name>John S. Skogtvedt</name>
		<description>Proxied maintainer</description>
	</maintainer>
	<maintainer type="project">
		<email>desktop-misc@gentoo.org</email>
		<name>Gentoo Desktop Miscellaneous Project</name>
	</maintainer>
	<maintainer type="project">
		<email>proxy-maint@gentoo.org</email>
		<name>Proxy Maintainers</name>
	</maintainer>
</pkgmetadata>
