<?xml version="1.0" encoding="UTF-8"?>
<!DOCTYPE pkgmetadata SYSTEM "http://www.gentoo.org/dtd/metadata.dtd">
<pkgmetadata>
	<herd>qemu</herd>
	<maintainer>
		<email>cardoe@gentoo.org</email>
		<name>Doug Goldstein</name>
	</maintainer>
	<longdescription lang="en">
		KVM (for Kernel-based Virtual Machine) is a full virtualization solution
		for Linux on x86 hardware containing virtualization extensions (Intel VT
		or AMD-V).  This package contains kernel modules for kvm.
	</longdescription>
	<upstream>
		<remote-id type="sourceforge">kvm</remote-id>
	</upstream>
</pkgmetadata>
