<?xml version="1.0" encoding="UTF-8"?>
<!DOCTYPE pkgmetadata SYSTEM "http://www.gentoo.org/dtd/metadata.dtd">
<pkgmetadata>
	<maintainer type="person">
		<email>sir.suriv@gmail.com</email>
		<name>Diogo Pereira</name>
	</maintainer>
	<maintainer type="person">
		<email>ck+gentoo@bl4ckb0x.de</email>
		<name>Conrad Kostecki</name>
	</maintainer>
	<maintainer type="project">
		<email>proxy-maint@gentoo.org</email>
		<name>Proxy Maintainers</name>
	</maintainer>
	<longdescription>
		j4-dmenu-desktop is a replacement for i3-dmenu-desktop.
		The purpose is to find .desktop files,
		but shell commands can also be executed.
	</longdescription>
	<upstream>
		<bugs-to>https://github.com/enkore/j4-dmenu-desktop/issues</bugs-to>
		<remote-id type="github">enkore/j4-dmenu-desktop</remote-id>
	</upstream>
</pkgmetadata>
