<?xml version="1.0" encoding="UTF-8"?>
<!DOCTYPE pkgmetadata SYSTEM "http://www.gentoo.org/dtd/metadata.dtd">
<pkgmetadata>
	<maintainer type="person">
		<email>marecki@gentoo.org</email>
		<name>Marek Szuba</name>
	</maintainer>
	<stabilize-allarches/>
	<longdescription>
		These Dictionary topics are from M.G. Easton M.A., D.D., Illustrated Bible
		Dictionary, Third Edition, published by Thomas Nelson, 1897. Due to the
		nature of etext, the illustrated portions of the Dictionary have not been
		included.
	</longdescription>
</pkgmetadata>
