<?xml version="1.0" encoding="UTF-8"?>
<!DOCTYPE pkgmetadata SYSTEM "https://www.gentoo.org/dtd/metadata.dtd">
<pkgmetadata>
  <maintainer type="person" proxied="yes">
    <email>julien@jroy.ca</email>
    <name>Julien Roy</name>
  </maintainer>
  <maintainer type="person" proxied="yes">
    <email>johnmh@johnmh.me</email>
    <name>John M. Harris, Jr.</name>
  </maintainer>
  <maintainer type="project" proxied="proxy">
    <email>proxy-maint@gentoo.org</email>
    <name>Proxy Maintainers</name>
  </maintainer>
  <upstream>
    <changelog>https://github.com/hyprwm/aquamarine/releases</changelog>
    <bugs-to>https://github.com/hyprwm/aquamarine/issues</bugs-to>
    <remote-id type="github">hyprwm/aquamarine</remote-id>
  </upstream>
</pkgmetadata>
