<?xml version="1.0" encoding="UTF-8"?>
<!DOCTYPE pkgmetadata SYSTEM "http://www.gentoo.org/dtd/metadata.dtd">
<pkgmetadata>
  <maintainer type="project">
    <email>sci@gentoo.org</email>
    <name>Gentoo Science Project</name>
  </maintainer>
  <longdescription lang="en">
  BONMIN (Basic Open-source Nonlinear Mixed INteger programming) is an
  open-source code for solving general MINLP (Mixed Integer NonLinear
  Programming) problems.
  </longdescription>
  <upstream>
    <remote-id type="github">coin-or/Bonmin</remote-id>
  </upstream>
</pkgmetadata>
